plone.app.robotframework-2.1.5-py3.13-nspkg.pth
plone/app/robotframework/__init__.py
plone/app/robotframework/_variables.robot
plone/app/robotframework/annotate.py
plone/app/robotframework/annotate.robot
plone/app/robotframework/autologin.py
plone/app/robotframework/browser.robot
plone/app/robotframework/config.py
plone/app/robotframework/content.py
plone/app/robotframework/genericsetup.py
plone/app/robotframework/i18n.py
plone/app/robotframework/keywords.py
plone/app/robotframework/keywords.robot
plone/app/robotframework/keywords.txt
plone/app/robotframework/mailhost.py
plone/app/robotframework/patches.py
plone/app/robotframework/pybabel.py
plone/app/robotframework/quickinstaller.py
plone/app/robotframework/reload.py
plone/app/robotframework/remote.py
plone/app/robotframework/robotentrypoints.py
plone/app/robotframework/saucelabs.py
plone/app/robotframework/saucelabs.robot
plone/app/robotframework/selenium.robot
plone/app/robotframework/server.py
plone/app/robotframework/server.robot
plone/app/robotframework/server.txt
plone/app/robotframework/speak.robot
plone/app/robotframework/testing.py
plone/app/robotframework/user.robot
plone/app/robotframework/users.py
plone/app/robotframework/utils.py
plone/app/robotframework/variables.py
plone/app/robotframework/variables.robot
plone/app/robotframework/content/file.pdf
plone/app/robotframework/content/image.jpg
plone/app/robotframework/selectors/cmfplone43.robot
plone/app/robotframework/selectors/cmfplone50.robot
plone/app/robotframework/selectors/cmfplone60.robot
plone/app/robotframework/tests/__init__.py
plone/app/robotframework/tests/test_autologin_library.robot
plone/app/robotframework/tests/test_browser_library.robot
plone/app/robotframework/tests/test_content.py
plone/app/robotframework/tests/test_content_library.robot
plone/app/robotframework/tests/test_i18n_library.robot
plone/app/robotframework/tests/test_quickinstaller_library.robot
plone/app/robotframework/tests/test_robot.py
plone_app_robotframework-2.1.5.dist-info/METADATA
plone_app_robotframework-2.1.5.dist-info/WHEEL
plone_app_robotframework-2.1.5.dist-info/entry_points.txt
plone_app_robotframework-2.1.5.dist-info/namespace_packages.txt
plone_app_robotframework-2.1.5.dist-info/top_level.txt
plone_app_robotframework-2.1.5.dist-info/RECORD
