Metadata-Version: 2.2
Name: plone.app.robotframework
Version: 2.1.5
Summary: Robot Framework testing resources for Plone
Home-page: https://github.com/plone/plone.app.robotframework/
Author: Asko Soukka
Author-email: asko.soukka@iki.fi
License: GPL
Keywords: robot automatic browser testing Plone
Classifier: Development Status :: 5 - Production/Stable
Classifier: Framework :: Plone
Classifier: Framework :: Plone :: 6.0
Classifier: Framework :: Plone :: 6.1
Classifier: License :: OSI Approved :: GNU General Public License (GPL)
Classifier: Programming Language :: Python
Classifier: Programming Language :: Python :: 3.8
Classifier: Programming Language :: Python :: 3.9
Classifier: Programming Language :: Python :: 3.10
Classifier: Programming Language :: Python :: 3.11
Classifier: Programming Language :: Python :: 3.12
Requires-Python: >=3.8
Requires-Dist: Pillow
Requires-Dist: Products.CMFPlone
Requires-Dist: Products.PlonePAS>=5.0.1
Requires-Dist: Products.PluggableAuthService
Requires-Dist: Zope
Requires-Dist: babel
Requires-Dist: docutils
Requires-Dist: plone.app.testing
Requires-Dist: plone.app.textfield
Requires-Dist: plone.base
Requires-Dist: plone.dexterity
Requires-Dist: plone.i18n
Requires-Dist: plone.namedfile
Requires-Dist: plone.protect
Requires-Dist: plone.registry
Requires-Dist: plone.testing
Requires-Dist: plone.uuid
Requires-Dist: robotframework
Requires-Dist: robotframework-selenium2library
Requires-Dist: robotframework-seleniumtestability
Requires-Dist: robotframework-browser
Requires-Dist: robotsuite
Requires-Dist: selenium
Requires-Dist: setuptools
Requires-Dist: z3c.form
Requires-Dist: z3c.relationfield
Requires-Dist: zope.component
Requires-Dist: zope.i18n
Requires-Dist: zope.intid
Requires-Dist: zope.schema
Requires-Dist: zope.testrunner
Provides-Extra: ride
Requires-Dist: robotframework-ride; extra == "ride"
Provides-Extra: speak
Requires-Dist: collective.js.speakjs; extra == "speak"
Provides-Extra: test
Requires-Dist: Products.MailHost; extra == "test"
Requires-Dist: plone.app.textfield; extra == "test"
Requires-Dist: plone.dexterity; extra == "test"
Requires-Dist: robotsuite; extra == "test"
Requires-Dist: webtest; extra == "test"
Requires-Dist: z3c.form; extra == "test"
Requires-Dist: zope.configuration; extra == "test"
Provides-Extra: reload
Requires-Dist: watchdog; extra == "reload"
Provides-Extra: docs
Requires-Dist: sphinxcontrib-robotdoc; extra == "docs"
Provides-Extra: debug
Requires-Dist: robotframework-debuglibrary; extra == "debug"
Dynamic: author
Dynamic: author-email
Dynamic: classifier
Dynamic: description
Dynamic: home-page
Dynamic: keywords
Dynamic: license
Dynamic: provides-extra
Dynamic: requires-dist
Dynamic: requires-python
Dynamic: summary
